{
  "version": "5",
  "dialect": "mysql",
  "id": "b33339ca-3347-491d-b45d-b113ca718a86",
  "prevId": "dccb70f7-1072-4b50-b688-500684834bea",
  "tables": {
    "events": {
      "name": "events",
      "columns": {
        "id": {
          "name": "id",
          "type": "int",
          "primaryKey": false,
          "notNull": true,
          "autoincrement": true
        },
        "name": {
          "name": "name",
          "type": "varchar(255)",
          "primaryKey": false,
          "notNull": true,
          "autoincrement": false
        },
        "description": {
          "name": "description",
          "type": "text",
          "primaryKey": false,
          "notNull": true,
          "autoincrement": false
        },
        "startDate": {
          "name": "startDate",
          "type": "timestamp",
          "primaryKey": false,
          "notNull": true,
          "autoincrement": false
        },
        "endDate": {
          "name": "endDate",
          "type": "timestamp",
          "primaryKey": false,
          "notNull": false,
          "autoincrement": false
        },
        "location": {
          "name": "location",
          "type": "varchar(255)",
          "primaryKey": false,
          "notNull": true,
          "autoincrement": false
        },
        "locationAddress": {
          "name": "locationAddress",
          "type": "text",
          "primaryKey": false,
          "notNull": false,
          "autoincrement": false
        },
        "locationLatitude": {
          "name": "locationLatitude",
          "type": "varchar(20)",
          "primaryKey": false,
          "notNull": false,
          "autoincrement": false
        },
        "locationLongitude": {
          "name": "locationLongitude",
          "type": "varchar(20)",
          "primaryKey": false,
          "notNull": false,
          "autoincrement": false
        },
        "organizerName": {
          "name": "organizerName",
          "type": "varchar(255)",
          "primaryKey": false,
          "notNull": true,
          "autoincrement": false
        },
        "organizerEmail": {
          "name": "organizerEmail",
          "type": "varchar(320)",
          "primaryKey": false,
          "notNull": true,
          "autoincrement": false
        },
        "organizerPhone": {
          "name": "organizerPhone",
          "type": "varchar(20)",
          "primaryKey": false,
          "notNull": false,
          "autoincrement": false
        },
        "organizerUrl": {
          "name": "organizerUrl",
          "type": "varchar(2048)",
          "primaryKey": false,
          "notNull": false,
          "autoincrement": false
        },
        "eventUrl": {
          "name": "eventUrl",
          "type": "varchar(2048)",
          "primaryKey": false,
          "notNull": false,
          "autoincrement": false
        },
        "imageUrl": {
          "name": "imageUrl",
          "type": "varchar(2048)",
          "primaryKey": false,
          "notNull": false,
          "autoincrement": false
        },
        "eventType": {
          "name": "eventType",
          "type": "enum('fundraiser','rally','meeting','training','social','other')",
          "primaryKey": false,
          "notNull": true,
          "autoincrement": false,
          "default": "'other'"
        },
        "visibility": {
          "name": "visibility",
          "type": "enum('public','private','members')",
          "primaryKey": false,
          "notNull": true,
          "autoincrement": false,
          "default": "'public'"
        },
        "status": {
          "name": "status",
          "type": "enum('pending','approved','rejected')",
          "primaryKey": false,
          "notNull": true,
          "autoincrement": false,
          "default": "'pending'"
        },
        "submittedBy": {
          "name": "submittedBy",
          "type": "int",
          "primaryKey": false,
          "notNull": true,
          "autoincrement": false
        },
        "submittedAt": {
          "name": "submittedAt",
          "type": "timestamp",
          "primaryKey": false,
          "notNull": true,
          "autoincrement": false,
          "default": "(now())"
        },
        "approvedBy": {
          "name": "approvedBy",
          "type": "int",
          "primaryKey": false,
          "notNull": false,
          "autoincrement": false
        },
        "approvedAt": {
          "name": "approvedAt",
          "type": "timestamp",
          "primaryKey": false,
          "notNull": false,
          "autoincrement": false
        },
        "rejectionReason": {
          "name": "rejectionReason",
          "type": "text",
          "primaryKey": false,
          "notNull": false,
          "autoincrement": false
        },
        "createdAt": {
          "name": "createdAt",
          "type": "timestamp",
          "primaryKey": false,
          "notNull": true,
          "autoincrement": false,
          "default": "(now())"
        },
        "updatedAt": {
          "name": "updatedAt",
          "type": "timestamp",
          "primaryKey": false,
          "notNull": true,
          "autoincrement": false,
          "onUpdate": true,
          "default": "(now())"
        }
      },
      "indexes": {},
      "foreignKeys": {},
      "compositePrimaryKeys": {
        "events_id": {
          "name": "events_id",
          "columns": [
            "id"
          ]
        }
      },
      "uniqueConstraints": {},
      "checkConstraint": {}
    },
    "users": {
      "name": "users",
      "columns": {
        "id": {
          "name": "id",
          "type": "int",
          "primaryKey": false,
          "notNull": true,
          "autoincrement": true
        },
        "openId": {
          "name": "openId",
          "type": "varchar(64)",
          "primaryKey": false,
          "notNull": true,
          "autoincrement": false
        },
        "name": {
          "name": "name",
          "type": "text",
          "primaryKey": false,
          "notNull": false,
          "autoincrement": false
        },
        "email": {
          "name": "email",
          "type": "varchar(320)",
          "primaryKey": false,
          "notNull": false,
          "autoincrement": false
        },
        "loginMethod": {
          "name": "loginMethod",
          "type": "varchar(64)",
          "primaryKey": false,
          "notNull": false,
          "autoincrement": false
        },
        "role": {
          "name": "role",
          "type": "enum('user','representative','admin')",
          "primaryKey": false,
          "notNull": true,
          "autoincrement": false,
          "default": "'user'"
        },
        "organization": {
          "name": "organization",
          "type": "varchar(255)",
          "primaryKey": false,
          "notNull": false,
          "autoincrement": false
        },
        "createdAt": {
          "name": "createdAt",
          "type": "timestamp",
          "primaryKey": false,
          "notNull": true,
          "autoincrement": false,
          "default": "(now())"
        },
        "updatedAt": {
          "name": "updatedAt",
          "type": "timestamp",
          "primaryKey": false,
          "notNull": true,
          "autoincrement": false,
          "onUpdate": true,
          "default": "(now())"
        },
        "lastSignedIn": {
          "name": "lastSignedIn",
          "type": "timestamp",
          "primaryKey": false,
          "notNull": true,
          "autoincrement": false,
          "default": "(now())"
        }
      },
      "indexes": {},
      "foreignKeys": {},
      "compositePrimaryKeys": {
        "users_id": {
          "name": "users_id",
          "columns": [
            "id"
          ]
        }
      },
      "uniqueConstraints": {
        "users_openId_unique": {
          "name": "users_openId_unique",
          "columns": [
            "openId"
          ]
        }
      },
      "checkConstraint": {}
    }
  },
  "views": {},
  "_meta": {
    "schemas": {},
    "tables": {},
    "columns": {}
  },
  "internal": {
    "tables": {},
    "indexes": {}
  }
}